{
	"info": {
		"_postman_id": "3a3dbe53-ebc7-450e-90d9-a054a7bcfda0",
		"name": "nodejs_practice",
		"schema": "https://schema.getpostman.com/json/collection/v2.1.0/collection.json"
	},
	"item": [
		{
			"name": "http://localhost:3000/articles",
			"request": {
				"method": "GET",
				"header": [],
				"url": {
					"raw": "http://localhost:3000/articles",
					"protocol": "http",
					"host": [
						"localhost"
					],
					"port": "3000",
					"path": [
						"articles"
					]
				}
			},
			"response": []
		},
		{
			"name": "http://localhost:3000/article",
			"request": {
				"method": "GET",
				"header": [],
				"url": {
					"raw": "http://localhost:3000/article/6217a339c9d27ee0426bfea5",
					"protocol": "http",
					"host": [
						"localhost"
					],
					"port": "3000",
					"path": [
						"article",
						"6217a339c9d27ee0426bfea5"
					]
				}
			},
			"response": []
		},
		{
			"name": "http://localhost:3000/articles",
			"request": {
				"method": "DELETE",
				"header": [],
				"url": {
					"raw": "http://localhost:3000/articles",
					"protocol": "http",
					"host": [
						"localhost"
					],
					"port": "3000",
					"path": [
						"articles"
					]
				}
			},
			"response": []
		},
		{
			"name": "http://localhost:3000/article",
			"request": {
				"method": "DELETE",
				"header": [],
				"body": {
					"mode": "raw",
					"raw": "{\r\n   \"_id\": \"6217a339c9d27ee0426bfea5\"\r\n}",
					"options": {
						"raw": {
							"language": "json"
						}
					}
				},
				"url": {
					"raw": "http://localhost:3000/article",
					"protocol": "http",
					"host": [
						"localhost"
					],
					"port": "3000",
					"path": [
						"article"
					]
				}
			},
			"response": []
		},
		{
			"name": "http://localhost:3000/article",
			"request": {
				"method": "PUT",
				"header": [],
				"body": {
					"mode": "raw",
					"raw": "{\r\n    \"_id\": \"6217a4e0ce19cb291012b6d4\",\r\n    \"title\": \"Title updated\",\r\n    \"text\": \"text updated\",\r\n    \"author\": \"Author updated\",\r\n    \"tag\": [\"node.js\", \"javascript\", \"mongodb\", \"updated\"]\r\n}",
					"options": {
						"raw": {
							"language": "json"
						}
					}
				},
				"url": {
					"raw": "http://localhost:3000/article",
					"protocol": "http",
					"host": [
						"localhost"
					],
					"port": "3000",
					"path": [
						"article"
					]
				}
			},
			"response": []
		},
		{
			"name": "http://localhost:3000/article",
			"request": {
				"method": "POST",
				"header": [],
				"body": {
					"mode": "raw",
					"raw": "{\r\n    \"title\": \"Title\",\r\n    \"text\": \"Lorem ipsum dolor sit amet, consectetur adipiscing elit, sed do eiusmod tempor incididunt ut labore et dolore magna aliqua.\",\r\n    \"author\": \"Author\",\r\n    \"tag\": [\"node.js\", \"javascript\", \"mongodb\"]\r\n}",
					"options": {
						"raw": {
							"language": "json"
						}
					}
				},
				"url": {
					"raw": "http://localhost:3000/article",
					"protocol": "http",
					"host": [
						"localhost"
					],
					"port": "3000",
					"path": [
						"article"
					]
				}
			},
			"response": []
		},
		{
			"name": "http://localhost:3000/articles",
			"request": {
				"method": "POST",
				"header": [],
				"body": {
					"mode": "raw",
					"raw": "{\r\n    \"articles\": [\r\n        {\r\n            \"title\": \"Title2\",\r\n            \"text\": \"Lorem ipsum dolor sit amet, consectetur adipiscing elit, sed do eiusmod tempor incididunt ut labore et dolore magna aliqua.\",\r\n            \"author\": \"Author\",\r\n            \"tag\": [\"node.js\", \"javascript\", \"mongodb\"]\r\n        },\r\n        {\r\n            \"title\": \"Title3\",\r\n            \"text\": \"Lorem ipsum dolor sit amet, consectetur adipiscing elit, sed do eiusmod tempor incididunt ut labore et dolore magna aliqua.\",\r\n            \"author\": \"Author\",\r\n            \"tag\": [\"node.js\", \"javascript\", \"mongodb\"]\r\n        }\r\n    ]\r\n}",
					"options": {
						"raw": {
							"language": "json"
						}
					}
				},
				"url": {
					"raw": "http://localhost:3000/articles",
					"protocol": "http",
					"host": [
						"localhost"
					],
					"port": "3000",
					"path": [
						"articles"
					]
				}
			},
			"response": []
		}
	]
}